nest_gen_accelerator_azure/__init__.py
nest_gen_accelerator_azure/components/output_parsers/__init__.py
nest_gen_accelerator_azure/components/output_parsers/base.py
nest_gen_accelerator_azure/components/output_parsers/json.py
nest_gen_accelerator_azure/components/outputs/__init__.py
nest_gen_accelerator_azure/components/outputs/call_to_action.py
nest_gen_accelerator_azure/components/outputs/exit_strategy.py
nest_gen_accelerator_azure/components/outputs/llm_response.py
nest_gen_accelerator_azure/exceptions/__init__.py
nest_gen_accelerator_azure/exceptions/exceptions.py
nest_gen_accelerator_azure/tools/__init__.py
nest_gen_accelerator_azure/tools/llm_tool.py
nest_gen_accelerator_azure/tools/utils.py
nest_gen_accelerator_azure/utils/__init__.py
nest_gen_accelerator_azure/utils/utils.py
nest_gen_accelerator_azure/yamls/llm_tool.yaml
nest_gen_accelerator_azure-1.2.3.dist-info/METADATA
nest_gen_accelerator_azure-1.2.3.dist-info/WHEEL
nest_gen_accelerator_azure-1.2.3.dist-info/entry_points.txt
nest_gen_accelerator_azure-1.2.3.dist-info/top_level.txt
nest_gen_accelerator_azure-1.2.3.dist-info/RECORD
