Metadata-Version: 2.1
Name: nest_gen_accelerator_azure
Version: 1.2.3
Summary: NestGen Accelerator Promptflow Package
